armada_logs/.gitignore
armada_logs/__init__.py
armada_logs/api/__init__.py
armada_logs/api/app_settings.py
armada_logs/api/assets.py
armada_logs/api/authentication.py
armada_logs/api/credential_profiles.py
armada_logs/api/data_sources.py
armada_logs/api/identity.py
armada_logs/api/logs.py
armada_logs/api/metrics.py
armada_logs/api/setup.py
armada_logs/app.py
armada_logs/cli.py
armada_logs/const.py
armada_logs/core/__init__.py
armada_logs/core/security.py
armada_logs/core/tasks.py
armada_logs/database/__init__.py
armada_logs/database/alembic/env.py
armada_logs/database/alembic/script.py.mako
armada_logs/database/alembic/versions/postgres/2025_01_12_1515-a39181de5d09_initial.py
armada_logs/database/alembic/versions/sqlite/2025_01_09_2010-dc8bdb03eb0a_initial.py
armada_logs/database/alembic.ini
armada_logs/database/alembic_commands.py
armada_logs/database/configurations.py
armada_logs/database/dependencies.py
armada_logs/database/query.py
armada_logs/jobs.py
armada_logs/lifespan.py
armada_logs/logging/__init__.py
armada_logs/logging/loggers.py
armada_logs/logging/logging.yaml
armada_logs/models/__init__.py
armada_logs/models/app_settings.py
armada_logs/models/assets.py
armada_logs/models/authentication.py
armada_logs/models/data_sources.py
armada_logs/models/logs.py
armada_logs/models/metrics.py
armada_logs/models/util.py
armada_logs/README.md
armada_logs/registry.py
armada_logs/resources/services.json
armada_logs/schema/__init__.py
armada_logs/schema/assets.py
armada_logs/schema/base.py
armada_logs/schema/data_sources.py
armada_logs/schema/identity_providers.py
armada_logs/schema/logs.py
armada_logs/schema/metrics.py
armada_logs/schema/roles.py
armada_logs/schema/settings.py
armada_logs/schema/users.py
armada_logs/schema/util.py
armada_logs/settings.py
armada_logs/sources/__init__.py
armada_logs/sources/aria_logs/__init__.py
armada_logs/sources/aria_logs/data_structures.py
armada_logs/sources/aria_logs/mapping.json
armada_logs/sources/aria_logs/source.py
armada_logs-0.1.1.dist-info/entry_points.txt
armada_logs-0.1.1.dist-info/LICENSE
armada_logs-0.1.1.dist-info/METADATA
armada_logs-0.1.1.dist-info/WHEEL
armada_logs-0.1.1.dist-info/RECORD
