Metadata-Version: 2.3
Name: armada-logs
Version: 0.1.1
Summary: Armada provides quick and detailed insights into network flows enriched with metadata
Home-page: https://github.com/Viter-0/armada
License: MIT
Keywords: log-analysis,vmware,nsx,logging,network,flows,firewall
Author: Viter
Author-email: viterr@proton.me
Requires-Python: >=3.11
Classifier: Intended Audience :: System Administrators
Classifier: License :: OSI Approved :: MIT License
Classifier: Programming Language :: Python :: 3
Classifier: Programming Language :: Python :: 3.11
Classifier: Programming Language :: Python :: 3.12
Classifier: Programming Language :: Python :: 3.13
Classifier: Topic :: Internet :: Log Analysis
Provides-Extra: all
Requires-Dist: aiosqlite (>=0.20.0)
Requires-Dist: alembic (>=1.14.0)
Requires-Dist: asyncpg (>=0.30.0)
Requires-Dist: bcrypt (>=4.2.1)
Requires-Dist: cryptography (>=44.0.0)
Requires-Dist: faker (>=33.3.0,<34.0.0) ; extra == "all"
Requires-Dist: fastapi-login (>=1.10.3)
Requires-Dist: fastapi[standard] (>=0.115.6)
Requires-Dist: httpx (>=0.28.1)
Requires-Dist: ldap3 (>=2.9.1)
Requires-Dist: pydantic (>=2.10.5)
Requires-Dist: pydantic-settings (>=2.7.1)
Requires-Dist: pyyaml (>=6.0.2)
Requires-Dist: sqlalchemy (>=2.0.36)
Requires-Dist: taskiq (>=0.11.10)
Requires-Dist: taskiq-redis (>=1.0.2)
Requires-Dist: truststore (>=0.10.0)
Requires-Dist: typer (>=0.15.1)
Requires-Dist: uvicorn (>=0.34.0)
Project-URL: Bug Tracker, https://github.com/Viter-0/armada/issues
Project-URL: Repository, https://github.com/Viter-0/armada
